[
  {
    "id": "angel",
    "name": "天使",
    "name_en": "Angel",
    "alignment_restrict": ["lg", "ng", "cg"],
    "type": "早期",
    "type_order": 1,
    "unlock_condition": null,
    "has_spellbook": true,
    "abilities": [
      { "rank": 1, "name": "天使之击", "type": "被动", "description": "神圣之力灌注武器，对邪恶目标造成额外1d6神圣伤害。每5级再+1d6。" },
      { "rank": 1, "name": "天堂之光", "type": "类法术", "description": "每日3+魅力调整值次，30英尺锥形神圣能量，治疗盟友1d6/等级，伤害邪恶生物。" },
      { "rank": 2, "name": "神圣恩典", "type": "被动", "description": "所有豁免+2。" },
      { "rank": 3, "name": "天使之盾", "type": "被动", "description": "AC+2偏斜加值。" },
      { "rank": 4, "name": "圣疗强化", "type": "被动", "description": "圣疗治疗量翻倍。" },
      { "rank": 7, "name": "天使之剑", "type": "类法术", "description": "召唤神圣长剑（每级1天）造成额外神圣伤害。" }
    ],
    "mythic_spells": [
      { "level": 1, "spell_ids": ["divine_favor"] },
      { "level": 2, "spell_ids": ["holy_smite"] },
      { "level": 3, "spell_ids": ["prayer"] },
      { "level": 4, "spell_ids": ["holy_sword"] },
      { "level": 5, "spell_ids": ["heal"] },
      { "level": 6, "spell_ids": ["greater_dispel_magic"] },
      { "level": 7, "spell_ids": ["holy_aura"] },
      { "level": 8, "spell_ids": ["mass_heal"] },
      { "level": 9, "spell_ids": ["gate"] },
      { "level": 10, "spell_ids": ["wish"] }
    ],
    "unique_mechanic": "独立法术书（道途径法术），天使道途拥有独立的神术法术列表。",
    "description": "天使道途践行善良之道，成为天堂的正义使者，用神圣力量扫除邪恶。"
  },
  {
    "id": "demon",
    "name": "恶魔",
    "name_en": "Demon",
    "alignment_restrict": ["ce"],
    "type": "早期",
    "type_order": 1,
    "unlock_condition": null,
    "has_spellbook": false,
    "abilities": [
      { "rank": 1, "name": "恶魔之爪", "type": "被动", "description": "获得2d6天生武器攻击。可造成流血伤害（1d6/轮）" },
      { "rank": 1, "name": "恶魔形态", "type": "类法术", "description": "变为恶魔形态，获得DR和能量抗力。" },
      { "rank": 2, "name": "恶魔抗力", "type": "被动", "description": "获得火焰/寒冷/闪电/强酸抗力5。" },
      { "rank": 3, "name": "恐惧光环", "type": "被动", "description": "邻近生物战栗，意志豁免无效。" },
      { "rank": 5, "name": "召唤恶魔", "type": "类法术", "description": "召唤恶魔协助战斗。" },
      { "rank": 8, "name": "恶魔化身", "type": "类法术", "description": "变为强大的恶魔真身。" }
    ],
    "unique_mechanic": "恶魔狂怒：进入狂怒状态获得力量和体质加值。",
    "description": "恶魔道途释放内心的狂暴，成为深渊的化身，以纯粹的毁灭之力碾压敌人。"
  },
  {
    "id": "lich",
    "name": "巫妖",
    "name_en": "Lich",
    "alignment_restrict": ["le", "ne", "ce"],
    "type": "早期",
    "type_order": 1,
    "unlock_condition": null,
    "has_spellbook": true,
    "abilities": [
      { "rank": 1, "name": "亡灵掌控", "type": "被动", "description": "你唤起的亡灵获得+2力量和+2敏捷。" },
      { "rank": 1, "name": "恐惧灵气", "type": "类法术", "description": "固定次数/天，释放恐惧灵气影响敌人。" },
      { "rank": 2, "name": "负能量掌握", "type": "被动", "description": "负能量法术伤害+50%。" },
      { "rank": 3, "name": "亡灵活化", "type": "类法术", "description": "活化亡灵为你战斗。" },
      { "rank": 5, "name": "腐化法术", "type": "被动", "description": "法术可对活物造成额外负能量伤害。" }
    ],
    "mythic_spells": [
      { "level": 1, "spell_ids": ["cause_fear"] },
      { "level": 2, "spell_ids": ["false_life"] },
      { "level": 3, "spell_ids": ["vampiric_touch"] },
      { "level": 4, "spell_ids": ["animate_dead"] },
      { "level": 5, "spell_ids": ["slay_living"] },
      { "level": 6, "spell_ids": ["circle_of_death"] },
      { "level": 7, "spell_ids": ["finger_of_death"] },
      { "level": 8, "spell_ids": ["horrid_wilting"] },
      { "level": 9, "spell_ids": ["power_word_kill"] },
      { "level": 10, "spell_ids": ["wail_of_the_banshee"] }
    ],
    "unique_mechanic": "独立法术书（道途径死灵法术），巫妖拥有独立的死灵法术列表。",
    "description": "巫妖道途追求超越死亡的禁忌力量，以亡灵大军和腐朽魔法征服一切。"
  },
  {
    "id": "azata",
    "name": "灵使",
    "name_en": "Azata",
    "alignment_restrict": ["cg", "ng", "cn"],
    "type": "早期",
    "type_order": 1,
    "unlock_condition": null,
    "has_spellbook": false,
    "abilities": [
      { "rank": 1, "name": "灵使之光", "type": "被动", "description": "盟友获得+2士气加值到攻击和伤害。" },
      { "rank": 1, "name": "鼓舞表演", "type": "类法术", "description": "每日3+魅调次，盟友获得临时生命和加速。" },
      { "rank": 2, "name": "自然魅力", "type": "被动", "description": "交涉和威吓+5。" },
      { "rank": 3, "name": "精灵盟友", "type": "类法术", "description": "召唤精类生物帮助战斗。" },
      { "rank": 5, "name": "生命链接", "type": "被动", "description": "与一个盟友建立链接，互相治疗。" }
    ],
    "unique_mechanic": "灵使羁绊：与一个盟友建立特殊链接，共享增益。",
    "description": "灵使道途拥抱自由和快乐，成为奔放的自由灵魂，用音乐和魔法鼓舞盟友。"
  },
  {
    "id": "aeon",
    "name": "御衡者",
    "name_en": "Aeon",
    "alignment_restrict": ["ln"],
    "type": "早期",
    "type_order": 1,
    "unlock_condition": null,
    "has_spellbook": false,
    "abilities": [
      { "rank": 1, "name": "均衡之眼", "type": "被动", "description": "察觉+5，可看穿隐形和幻术。" },
      { "rank": 1, "name": "秩序之触", "type": "类法术", "description": "每日3+感知调整值次。接触消除buff或debuff。" },
      { "rank": 2, "name": "均衡净化", "type": "被动", "description": "每日固定次数。移除区域内的魔法效果。" },
      { "rank": 4, "name": "时间锁定", "type": "类法术", "description": "固定难度下对敌人进行时间停止攻击。" },
      { "rank": 7, "name": "均衡仲裁", "type": "类法术", "description": "范围判决：移除所有非法状态。" }
    ],
    "unique_mechanic": "均衡裁决：用秩序力量强制恢复平衡状态。",
    "description": "御衡者道途捍卫多元宇宙的平衡法则，用秩序力量纠正一切失衡。"
  },
  {
    "id": "trickster",
    "name": "诡术大师",
    "name_en": "Trickster",
    "alignment_restrict": ["cn", "ce", "cg", "n"],
    "type": "早期",
    "type_order": 1,
    "unlock_condition": null,
    "has_spellbook": false,
    "abilities": [
      { "rank": 1, "name": "直觉闪避", "type": "被动", "description": "不被夹击；反射豁免+2。" },
      { "rank": 1, "name": "诡计攻击", "type": "被动", "description": "攻击时可造成额外1d6偷袭伤害，每5级再+1d6。" },
      { "rank": 2, "name": "魔术手法", "type": "被动", "description": "解除装置和使用魔法装置+5。" },
      { "rank": 3, "name": "误导", "type": "类法术", "description": "每日3次。将一个敌军的目标转移给另一个敌军。" },
      { "rank": 5, "name": "精通诡计", "type": "被动", "description": "获得一个额外游荡者天赋。" },
      { "rank": 8, "name": "颠覆", "type": "类法术", "description": "反转一个法术或效果的目标。" }
    ],
    "unique_mechanic": "诡术：获得各种打破规则的特殊能力。",
    "description": "诡术大师道途玩弄命运本身，用计谋和巧合将敌人引入荒诞的结局。"
  },
  {
    "id": "gold_dragon",
    "name": "金龙",
    "name_en": "Gold Dragon",
    "alignment_restrict": ["lg", "ng", "cg"],
    "type": "后期",
    "type_order": 2,
    "unlock_condition": "必须选择过天使或灵使道途，并在神话等级8时触发相关任务线。",
    "has_spellbook": false,
    "abilities": [
      { "rank": 1, "name": "龙形态", "description": "变为金龙形态。获得飞行能力，天生护甲+4，力量+4。" },
      { "rank": 2, "name": "龙息", "description": "锥形火焰龙息（每级1d10）。" },
      { "rank": 3, "name": "钢铁意志", "description": "免疫恐惧和魅惑。" },
      { "rank": 5, "name": "龙之威压", "description": "每级1次释放龙威恐惧敌人。" }
    ],
    "unique_mechanic": "龙之变身：可在人形和龙形态之间切换。",
    "description": "金龙道途是救赎之路，前邪恶之人可以通过此道途重获新生，变成正义的金龙。"
  },
  {
    "id": "devil",
    "name": "魔鬼",
    "name_en": "Devil",
    "alignment_restrict": ["le"],
    "type": "后期",
    "type_order": 2,
    "unlock_condition": "必须选择过御衡者或巫妖（可能）或诡术大师道途，在神话等级8时触发。",
    "has_spellbook": false,
    "abilities": [
      { "rank": 1, "name": "炼狱形态", "description": "获得魔鬼外形，DR5/善良，能量抗力。" },
      { "rank": 2, "name": "契约", "description": "可与盟友签订契约，双方获益。" },
      { "rank": 3, "name": "地狱火焰", "description": "近战附加2d6地狱火焰伤害。" },
      { "rank": 4, "name": "心灵控制", "description": "支配类人生物每日1次。" }
    ],
    "unique_mechanic": "魔鬼契约：与盟友签订契约双方获得特殊增益。",
    "description": "魔鬼道途走向绝对的秩序和权力，用狡诈和契约统治一切。"
  },
  {
    "id": "swarm",
    "name": "虫群",
    "name_en": "Swarm-That-Walks",
    "alignment_restrict": ["ce"],
    "type": "后期",
    "type_order": 2,
    "unlock_condition": "必须选择过恶魔道途，并在神话等级8时触发相关任务线。",
    "has_spellbook": false,
    "abilities": [
      { "rank": 1, "name": "虫群形态", "description": "身体化作无数虫群。获得DR10/-，免疫武器伤害（除区域武器）。" },
      { "rank": 2, "name": "吞噬", "description": "吞噬倒地敌人获得临时生命和属性加值。" },
      { "rank": 3, "name": "虫群蔓延", "description": "虫群攻击造成1d6敏捷伤害。" },
      { "rank": 5, "name": "虫群意志", "description": "免疫心智效果，每个虫群都承载你的意志。" }
    ],
    "unique_mechanic": "虫群：你是无数虫子的集合体，免疫大部分物理攻击。",
    "description": "虫群道途抛弃人性，成为亿万虫子的集合体，以无尽的数量吞噬一切生物。"
  },
  {
    "id": "legend",
    "name": "传奇",
    "name_en": "Legend",
    "alignment_restrict": ["lg", "ln", "le", "ng", "n", "ne", "cg", "cn", "ce"],
    "type": "传奇",
    "type_order": 3,
    "unlock_condition": "在神话等级8时放弃所有神话力量，问心无愧地走上自己的道路。",
    "has_spellbook": false,
    "abilities": [
      { "rank": 1, "name": "传说之力", "description": "总等级上限突破40级（得到额外20级）。" },
      { "rank": 2, "name": "非凡坚韧", "description": "所有豁免+4。" },
      { "rank": 3, "name": "传奇之躯", "description": "所有属性+2。" },
      { "rank": 5, "name": "传说技能", "description": "选择一项技能获得+10加值。" }
    ],
    "unique_mechanic": "等级上限突破：角色等级上限提升至40级。",
    "description": "传奇道途拒绝神话力量，依靠纯粹的人性达到力量的极致。等级上限突破至40级。"
  }
]
